pycube/__init__.py
pycube/core.py
pycube/module.py
pycube/regulario.py
pycube/memory/__init__.py
pycube/memory/state.py
pycube/network/__init__.py
pycube/network/api_gateway.py
publish_test_8368822371-0.0.3.dist-info/LICENSE
publish_test_8368822371-0.0.3.dist-info/METADATA
publish_test_8368822371-0.0.3.dist-info/WHEEL
publish_test_8368822371-0.0.3.dist-info/top_level.txt
publish_test_8368822371-0.0.3.dist-info/RECORD
