Metadata-Version: 2.1
Name: publish-test-8368822371
Version: 0.0.3
Summary: A framework for building microservices.
Home-page: https://gitlab.com/koktszhozelca/pycube
Author: Kok Tsz Ho Zelca
Author-email: zelcakok@outlook.com
License: UNKNOWN
Project-URL: Bug Tracker, https://gitlab.com/koktszhozelca/pycube/-/issues
Project-URL: Source Code, https://gitlab.com/koktszhozelca/pycube
Platform: UNKNOWN
Classifier: Programming Language :: Python :: 3
Classifier: License :: OSI Approved :: MIT License
Classifier: Operating System :: OS Independent
Requires-Python: >=3.6
Requires-Dist: aiohttp (==3.6.2)
Requires-Dist: async-timeout (==3.0.1)
Requires-Dist: attrs (==20.2.0)
Requires-Dist: chardet (==3.0.4)
Requires-Dist: idna (==2.10)
Requires-Dist: multidict (==4.7.6)
Requires-Dist: typing-extensions (==3.7.4.3)
Requires-Dist: yarl (==1.5.1)
